pycomm3/__init__.py
pycomm3/_version.py
pycomm3/cip_driver.py
pycomm3/const.py
pycomm3/custom_types.py
pycomm3/exceptions.py
pycomm3/logger.py
pycomm3/logix_driver.py
pycomm3/map.py
pycomm3/py.typed
pycomm3/slc_driver.py
pycomm3/socket_.py
pycomm3/tag.py
pycomm3/util.py
pycomm3/cip/__init__.py
pycomm3/cip/data_types.py
pycomm3/cip/object_library.py
pycomm3/cip/pccc.py
pycomm3/cip/services.py
pycomm3/cip/status_info.py
pycomm3/packets/__init__.py
pycomm3/packets/base.py
pycomm3/packets/cip.py
pycomm3/packets/ethernetip.py
pycomm3/packets/logix.py
pycomm3/packets/util.py
pycomm3-1.2.15.dist-info/licenses/LICENSE
pycomm3-1.2.15.dist-info/METADATA
pycomm3-1.2.15.dist-info/WHEEL
pycomm3-1.2.15.dist-info/top_level.txt
pycomm3-1.2.15.dist-info/RECORD
